Evtx/BinaryParser.py
Evtx/Evtx.py
Evtx/Nodes.py
Evtx/Views.py
Evtx/__init__.py
python_evtx-0.8.0.dist-info/licenses/LICENSE.TXT
python_evtx-0.8.0.dist-info/METADATA
python_evtx-0.8.0.dist-info/WHEEL
python_evtx-0.8.0.dist-info/entry_points.txt
python_evtx-0.8.0.dist-info/top_level.txt
python_evtx-0.8.0.dist-info/RECORD
