Metadata-Version: 2.4
Name: python-evtx
Version: 0.8.0
Summary: Pure Python parser for Windows event log files (.evtx).
Author-email: Willi Ballenthin <willi.ballenthin@gmail.com>
License-Expression: Apache-2.0
Project-URL: Homepage, https://github.com/williballenthin/python-evtx
Project-URL: Repository, https://github.com/williballenthin/python-evtx
Project-URL: Bug-Tracker, https://github.com/williballenthin/python-evtx/issues
Classifier: Development Status :: 5 - Production/Stable
Classifier: Intended Audience :: Developers
Classifier: Intended Audience :: Information Technology
Classifier: Operating System :: OS Independent
Classifier: Programming Language :: Python :: 3
Classifier: Programming Language :: Python :: 3.9
Classifier: Programming Language :: Python :: 3.10
Classifier: Programming Language :: Python :: 3.11
Classifier: Programming Language :: Python :: 3.12
Classifier: Programming Language :: Python :: 3.13
Classifier: Topic :: System :: Logging
Classifier: Topic :: Software Development :: Libraries :: Python Modules
Classifier: Topic :: Security
Requires-Python: >=3.9
License-File: LICENSE.TXT
Requires-Dist: hexdump>=3.3
Provides-Extra: test
Requires-Dist: pytest-cov>=5.0.0; extra == "test"
Requires-Dist: pytest>=8.2.2; extra == "test"
Requires-Dist: lxml>=5.2.2; extra == "test"
Requires-Dist: black>=24.4.2; extra == "test"
Requires-Dist: isort>=5.13.2; extra == "test"
Requires-Dist: ruff>=0.4.10; extra == "test"
Dynamic: license-file
